Memes_And_Jokes/__init__.py
Memes_And_Jokes/jokes.py
Memes_And_Jokes/memes.py
memes_and_jokes-1.0.0.dist-info/LICENCE.txt
memes_and_jokes-1.0.0.dist-info/METADATA
memes_and_jokes-1.0.0.dist-info/WHEEL
memes_and_jokes-1.0.0.dist-info/top_level.txt
memes_and_jokes-1.0.0.dist-info/RECORD
